vox_box/__init__.py
vox_box/backends/stt/base.py
vox_box/backends/stt/faster_whisper.py
vox_box/backends/stt/funasr.py
vox_box/backends/tts/bark.py
vox_box/backends/tts/base.py
vox_box/backends/tts/cosyvoice.py
vox_box/backends/tts/cosyvoice_spk2info.pt
vox_box/backends/tts/dia.py
vox_box/cmd/__init__.py
vox_box/cmd/start.py
vox_box/cmd/version.py
vox_box/config/__init__.py
vox_box/config/config.py
vox_box/downloader/downloaders.py
vox_box/downloader/hub.py
vox_box/estimator/bark.py
vox_box/estimator/base.py
vox_box/estimator/cosyvoice.py
vox_box/estimator/dia.py
vox_box/estimator/estimate.py
vox_box/estimator/faster_whisper.py
vox_box/estimator/funasr.py
vox_box/logging.py
vox_box/main.py
vox_box/server/app.py
vox_box/server/model.py
vox_box/server/routers.py
vox_box/server/server.py
vox_box/third_party/CosyVoice/.git
vox_box/third_party/CosyVoice/.github/ISSUE_TEMPLATE/bug_report.md
vox_box/third_party/CosyVoice/.github/ISSUE_TEMPLATE/feature_request.md
vox_box/third_party/CosyVoice/.github/workflows/lint.yml
vox_box/third_party/CosyVoice/.github/workflows/stale-issues.yml
vox_box/third_party/CosyVoice/.gitignore
vox_box/third_party/CosyVoice/.gitmodules
vox_box/third_party/CosyVoice/CODE_OF_CONDUCT.md
vox_box/third_party/CosyVoice/FAQ.md
vox_box/third_party/CosyVoice/LICENSE
vox_box/third_party/CosyVoice/README.md
vox_box/third_party/CosyVoice/asset/dingding.png
vox_box/third_party/CosyVoice/cosyvoice/__init__.py
vox_box/third_party/CosyVoice/cosyvoice/bin/average_model.py
vox_box/third_party/CosyVoice/cosyvoice/bin/export_jit.py
vox_box/third_party/CosyVoice/cosyvoice/bin/export_onnx.py
vox_box/third_party/CosyVoice/cosyvoice/bin/export_trt.sh
vox_box/third_party/CosyVoice/cosyvoice/bin/inference.py
vox_box/third_party/CosyVoice/cosyvoice/bin/train.py
vox_box/third_party/CosyVoice/cosyvoice/cli/__init__.py
vox_box/third_party/CosyVoice/cosyvoice/cli/cosyvoice.py
vox_box/third_party/CosyVoice/cosyvoice/cli/frontend.py
vox_box-0.0.21.dist-info/LICENSE
vox_box-0.0.21.dist-info/METADATA
vox_box-0.0.21.dist-info/WHEEL
vox_box-0.0.21.dist-info/entry_points.txt
vox_box-0.0.21.dist-info/RECORD
